jsonconfig/__init__.py
jsonconfig/_compat.py
jsonconfig/appdir.py
jsonconfig/core.py
jsonconfig/env.py
jsonconfig/errors.py
jsonconfig/jsonutils.py
jsonconfig/kwargs.py
jsonconfig/pwd.py
jsonconfig/shortcuts.py
jsonconfig_tool-1.5.dist-info/DESCRIPTION.rst
jsonconfig_tool-1.5.dist-info/METADATA
jsonconfig_tool-1.5.dist-info/RECORD
jsonconfig_tool-1.5.dist-info/WHEEL
jsonconfig_tool-1.5.dist-info/metadata.json
jsonconfig_tool-1.5.dist-info/top_level.txt
