Metadata-Version: 1.2
Name: jsonconfig-tool
Version: 1.5
Summary: Configuration made easy: JSON, encrypted, envvars, etc.
Home-page: http://github.com/json-transformations/jsonconfig
Author: Brian Peterson
Author-email: bpeterso2000@yahoo.com
License: MIT
Keywords: config configuration json encryption passwords simple easy
Platform: UNKNOWN
Classifier: License :: OSI Approved :: MIT License
Classifier: Intended Audience :: Developers
Classifier: Topic :: Software Development
Classifier: Topic :: Utilities
Classifier: Programming Language :: Python
Classifier: Programming Language :: Python :: 2.7
Classifier: Programming Language :: Python :: 3
Requires-Python: >=2.7
